license
multipartformdata/__init__.py
multipartformdata/Multipart.py
multipartformdata-1.4.dist-info/entry_points.txt
multipartformdata-1.4.dist-info/license
multipartformdata-1.4.dist-info/WHEEL
multipartformdata-1.4.dist-info/METADATA
multipartformdata-1.4.dist-info/RECORD
