Metadata-Version: 2.1
Name: multipartformdata
Version: 1.4
Summary: Convert the request data to form-data.
Home-page: https://github.com/HttpTesting/MultipartFormData
License: Apache-2.0
Keywords: http,api,form-data,content-type
Author: 天枢
Author-email: lengyaohui@163.com
Requires-Python: >=3.5,<4.0
Classifier: Development Status :: 3 - Alpha
Classifier: Environment :: Console
Classifier: License :: OSI Approved :: Apache Software License
Classifier: Programming Language :: Python :: 3
Classifier: Programming Language :: Python :: 3.5
Classifier: Programming Language :: Python :: 3.6
Classifier: Programming Language :: Python :: 3.7
Classifier: Topic :: Software Development :: Documentation
Classifier: Topic :: Software Development :: Libraries :: Python Modules
Project-URL: Repository, https://github.com/HttpTesting/MultipartFormData
